{
  "date": "2026-07-20",
  "summaries": [
    {
      "filename": "seranking-backlinks-www-tullylegal-com.json",
      "competitorId": "www-tullylegal-com",
      "type": "backlinks",
      "rowCount": 52,
      "topRows": [
        {
          "source_page": "https://newsinsights.org/trumps-top-man-immediately-quits-no-explanation/",
          "source_page_title": "Trumps TOP Man Immediately QUITS – No Explanation! | News Insights",
          "target_page": "https://www.tullylegal.com/our-firm/news/at-least-15-senior-cbp-employees-were-pushed-out-under-noem-sources/",
          "anchor": "Web – At least 15 senior CBP employees were pushed out under …",
          "domain_authority": "11",
          "page_authority": "0",
          "nofollow": "no",
          "first_seen": "2026-07-20"
        },
        {
          "source_page": "https://abogadosdefamiliatexas.com/recursos/localizador-de-abogados/",
          "source_page_title": "Abogado de Familia en Houston TX: Encuentra un Abogado",
          "target_page": "https://www.tullylegal.com/locations/rochester-ny/?refPageViewId=6bd9bc45165bc7fe",
          "anchor": "Christine F Redfield",
          "domain_authority": "14",
          "page_authority": "0",
          "nofollow": "no",
          "first_seen": "2026-07-20"
        },
        {
          "source_page": "http://preparedmealsdatenko.blogspot.com/2016/12/best-way-to-prepare-meals-for-week.html",
          "source_page_title": "Prepared Meals: Best Way To Prepare Meals For The Week",
          "target_page": "http://www.tullylegal.com/forms/Executors_Handbook.pdf",
          "anchor": "... Fetch Doc",
          "domain_authority": "1",
          "page_authority": "0",
          "nofollow": "no",
          "first_seen": "2026-07-19"
        },
        {
          "source_page": "http://preparedmealsdatenko.blogspot.com/2016/12/best-way-to-prepare-meals-for-week.html",
          "source_page_title": "Prepared Meals: Best Way To Prepare Meals For The Week",
          "target_page": "http://www.tullylegal.com/forms/Executors_Handbook.pdf",
          "anchor": "WHAT EVERY EXECUTOR OUGT TO KNOW - Divorce Lawyer",
          "domain_authority": "1",
          "page_authority": "0",
          "nofollow": "no",
          "first_seen": "2026-07-19"
        },
        {
          "source_page": "https://www.topteny.com/best-family-and-divorce-lawyers-in-usa/",
          "source_page_title": "Navigating Transitions: The Top 10 Family Divorce Lawyers in the USA",
          "target_page": "https://www.tullylegal.com/attorneys/",
          "anchor": "Jennifer J. Corcoran",
          "domain_authority": "67",
          "page_authority": "13",
          "nofollow": "no",
          "first_seen": "2026-07-18"
        },
        {
          "source_page": "https://www.topteny.com/best-family-and-divorce-lawyers-in-usa/",
          "source_page_title": "Navigating Transitions: The Top 10 Family Divorce Lawyers in the USA",
          "target_page": "https://www.tullylegal.com/attorneys/barbara-j-king/",
          "anchor": "Barbara King",
          "domain_authority": "67",
          "page_authority": "13",
          "nofollow": "no",
          "first_seen": "2026-07-18"
        },
        {
          "source_page": "https://firmranker.com/tully-rinckey-pllc",
          "source_page_title": "Tully Rinckey PLLC — Washington, DC | FirmRanker",
          "target_page": "https://www.tullylegal.com/locations/washington-dc",
          "anchor": "https://www.tullylegal.com/locations/washington-dc",
          "domain_authority": "13",
          "page_authority": "0",
          "nofollow": "yes",
          "first_seen": "2026-07-18"
        },
        {
          "source_page": "https://www.fedtools.com/blog/opm-suitability-rule-debarment-2026",
          "source_page_title": "OPM's New Rule Can Debar You From All Federal Jobs | FedTools",
          "target_page": "https://www.tullylegal.com/resources/articles/what-opms-suitability-changes-mean-for-federal-employees-the-basics/",
          "anchor": "Tully Rinckey analysis",
          "domain_authority": "6",
          "page_authority": "0",
          "nofollow": "no",
          "first_seen": "2026-07-18"
        },
        {
          "source_page": "https://www.tullyrinckey.com/our-team/patrick-oleksiak/",
          "source_page_title": "Patrick Oleksiak | Our Team | Tully Rinckey America Service Corporation",
          "target_page": "http://www.tullylegal.com/",
          "anchor": "WWW.TULLYLEGAL.COM",
          "domain_authority": "50",
          "page_authority": "0",
          "nofollow": "no",
          "first_seen": "2026-07-17"
        },
        {
          "source_page": "https://www.tullyrinckey.com/our-team/patrick-oleksiak/",
          "source_page_title": "Patrick Oleksiak | Our Team | Tully Rinckey America Service Corporation",
          "target_page": "http://www.tullylegal.com/",
          "anchor": "You are visiting the website for Tullly Rinckey America Service Corporation. If you are looking for legal services, please click here to visit www.tullylegal.com.",
          "domain_authority": "50",
          "page_authority": "0",
          "nofollow": "no",
          "first_seen": "2026-07-17"
        },
        {
          "source_page": "https://www.tullyrinckey.com/our-team/victoria-rose/",
          "source_page_title": "Victoria Rose | Our Team | Tully Rinckey America Service Corporation",
          "target_page": "http://www.tullylegal.com/",
          "anchor": "You are visiting the website for Tullly Rinckey America Service Corporation. If you are looking for legal services, please click here to visit www.tullylegal.com.",
          "domain_authority": "50",
          "page_authority": "0",
          "nofollow": "no",
          "first_seen": "2026-07-17"
        },
        {
          "source_page": "https://www.tullyrinckey.com/our-team/victoria-rose/",
          "source_page_title": "Victoria Rose | Our Team | Tully Rinckey America Service Corporation",
          "target_page": "http://www.tullylegal.com/",
          "anchor": "WWW.TULLYLEGAL.COM",
          "domain_authority": "50",
          "page_authority": "0",
          "nofollow": "no",
          "first_seen": "2026-07-17"
        },
        {
          "source_page": "https://www.waytolegal.com/legal-help-guides/understanding-noncompete-agreements-texas/",
          "source_page_title": "Understanding Noncompete Agreements in Texas",
          "target_page": "https://www.tullylegal.com/resources/articles/2026-update-clarifying-the-legal-status-of-non-competes-in-texas/",
          "anchor": "https://www.tullylegal.com/resources/articles/2026-update-clarifying-the-legal-status-of-non-competes-in-texas/",
          "domain_authority": "4",
          "page_authority": "0",
          "nofollow": "yes",
          "first_seen": "2026-07-17"
        },
        {
          "source_page": "https://www.trustandestates.com/practice-areas/matrimonial-law/matrimonial-asset-tracing/",
          "source_page_title": "Matrimonial Asset Tracing in New York Divorce Cases | NY Family Law Lawyer New York Estate Legacy Lawyers",
          "target_page": "https://www.tullylegal.com/resources/articles/how-is-marital-property-determined-in-new-york/",
          "anchor": "How Is Marital Property Determined In New York? – Tully Rinckey PLLC",
          "domain_authority": "6",
          "page_authority": "0",
          "nofollow": "no",
          "first_seen": "2026-07-17"
        },
        {
          "source_page": "https://www.trustandestates.com/practice-areas/elder-law/medicaid-planning/",
          "source_page_title": "New York Medicaid Planning: Secure Your Future & Assets | NY Elder Law Lawyer New York Estate Legacy Lawyers",
          "target_page": "https://www.tullylegal.com/resources/articles/medicaid-planning-in-new-york-protecting-assets-for-long-term-care/",
          "anchor": "https://www.tullylegal.com/resources/articles/medicaid-planning-in-new-york-protecting-assets-for-long-term-care/",
          "domain_authority": "6",
          "page_authority": "0",
          "nofollow": "no",
          "first_seen": "2026-07-17"
        },
        {
          "source_page": "https://www.tullyrinckey.com/our-team/joann-cannone/",
          "source_page_title": "JoAnn Cannone | Our Team | Tully Rinckey America Service Corporation",
          "target_page": "http://www.tullylegal.com/",
          "anchor": "WWW.TULLYLEGAL.COM",
          "domain_authority": "50",
          "page_authority": "0",
          "nofollow": "no",
          "first_seen": "2026-07-16"
        },
        {
          "source_page": "https://www.tullyrinckey.com/our-team/joann-cannone/",
          "source_page_title": "JoAnn Cannone | Our Team | Tully Rinckey America Service Corporation",
          "target_page": "http://www.tullylegal.com/",
          "anchor": "You are visiting the website for Tullly Rinckey America Service Corporation. If you are looking for legal services, please click here to visit www.tullylegal.com.",
          "domain_authority": "50",
          "page_authority": "0",
          "nofollow": "no",
          "first_seen": "2026-07-16"
        },
        {
          "source_page": "https://www.tullyrinckey.com/our-team/maggie-law/",
          "source_page_title": "Maggie Law | Our Team | Tully Rinckey America Service Corporation",
          "target_page": "http://www.tullylegal.com/",
          "anchor": "You are visiting the website for Tullly Rinckey America Service Corporation. If you are looking for legal services, please click here to visit www.tullylegal.com.",
          "domain_authority": "50",
          "page_authority": "0",
          "nofollow": "no",
          "first_seen": "2026-07-16"
        },
        {
          "source_page": "https://www.tullyrinckey.com/our-team/maggie-law/",
          "source_page_title": "Maggie Law | Our Team | Tully Rinckey America Service Corporation",
          "target_page": "http://www.tullylegal.com/",
          "anchor": "WWW.TULLYLEGAL.COM",
          "domain_authority": "50",
          "page_authority": "0",
          "nofollow": "no",
          "first_seen": "2026-07-16"
        },
        {
          "source_page": "https://www.tullyrinckey.com/our-team/richard-baetz/",
          "source_page_title": "Richard Baetz | Our Team | Tully Rinckey America Service Corporation",
          "target_page": "http://www.tullylegal.com/",
          "anchor": "WWW.TULLYLEGAL.COM",
          "domain_authority": "50",
          "page_authority": "0",
          "nofollow": "no",
          "first_seen": "2026-07-16"
        },
        {
          "source_page": "https://www.tullyrinckey.com/our-team/richard-baetz/",
          "source_page_title": "Richard Baetz | Our Team | Tully Rinckey America Service Corporation",
          "target_page": "http://www.tullylegal.com/",
          "anchor": "You are visiting the website for Tullly Rinckey America Service Corporation. If you are looking for legal services, please click here to visit www.tullylegal.com.",
          "domain_authority": "50",
          "page_authority": "0",
          "nofollow": "no",
          "first_seen": "2026-07-16"
        },
        {
          "source_page": "https://legalreview0.wixsite.com/biglegalreview",
          "source_page_title": "HOME | Biglegalreview",
          "target_page": "https://www.tullylegal.com/",
          "anchor": "tullylegal.com",
          "domain_authority": "20",
          "page_authority": "4",
          "nofollow": "no",
          "first_seen": "2026-07-16"
        },
        {
          "source_page": "https://nationalprobateservices.com/listing/kevin-yeager/",
          "source_page_title": "Kevin Yeager – National Probate Services",
          "target_page": "https://www.tullylegal.com/attorneys/kevin-h-yeager/",
          "anchor": "https://www.tullylegal.com/attorneys/kevin-h-yeager/",
          "domain_authority": "20",
          "page_authority": "0",
          "nofollow": "no",
          "first_seen": "2026-07-16"
        },
        {
          "source_page": "https://nationalprobateservices.com/listing/stanley-greenberg/",
          "source_page_title": "Stanley Greenberg – National Probate Services",
          "target_page": "https://www.tullylegal.com/attorneys/kevin-h-yeager/",
          "anchor": "https://www.tullylegal.com/attorneys/kevin-h-yeager/",
          "domain_authority": "20",
          "page_authority": "0",
          "nofollow": "no",
          "first_seen": "2026-07-16"
        },
        {
          "source_page": "https://nationalprobateservices.com/listing/william-logan/",
          "source_page_title": "William Logan – National Probate Services",
          "target_page": "https://www.tullylegal.com/attorneys/michael-c-fallings/",
          "anchor": "https://www.tullylegal.com/attorneys/michael-c-fallings/",
          "domain_authority": "20",
          "page_authority": "0",
          "nofollow": "no",
          "first_seen": "2026-07-16"
        }
      ]
    },
    {
      "filename": "seranking-keywords-www-tullylegal-com.json",
      "competitorId": "www-tullylegal-com",
      "type": "positions",
      "rowCount": 100,
      "topRows": [
        {
          "keyword": "family law attorney",
          "position": "12",
          "previous_position": "",
          "position_change": "new",
          "url": "https://www.tullylegal.com/manhattan-family/",
          "search_volume": "301000",
          "cpc": "3.9",
          "difficulty": "56",
          "estimated_traffic": "3437"
        },
        {
          "keyword": "employment lawyers near me",
          "position": "16",
          "previous_position": "18",
          "position_change": "+2",
          "url": "https://www.tullylegal.com/new-york-employment-law/",
          "search_volume": "60500",
          "cpc": "2.23",
          "difficulty": "50",
          "estimated_traffic": "773"
        },
        {
          "keyword": "family lawyer near me",
          "position": "28",
          "previous_position": "",
          "position_change": "new",
          "url": "https://www.tullylegal.com/albany-family/",
          "search_volume": "74000",
          "cpc": "2.75",
          "difficulty": "63",
          "estimated_traffic": "617"
        },
        {
          "keyword": "child support lawyer",
          "position": "23",
          "previous_position": "31",
          "position_change": "+8",
          "url": "https://www.tullylegal.com/brooklyn-family/child-support/",
          "search_volume": "60500",
          "cpc": "2.64",
          "difficulty": "55",
          "estimated_traffic": "339"
        },
        {
          "keyword": "will and trust",
          "position": "14",
          "previous_position": "25",
          "position_change": "+11",
          "url": "https://www.tullylegal.com/resources/articles/what-is-the-difference-between-a-will-and-a-trust-in-new-york-state/",
          "search_volume": "60500",
          "cpc": "2.54",
          "difficulty": "67",
          "estimated_traffic": "339"
        },
        {
          "keyword": "rinckey",
          "position": "1",
          "previous_position": "1",
          "position_change": "0",
          "url": "https://www.tullylegal.com/",
          "search_volume": "1500",
          "cpc": "3.97",
          "difficulty": "57",
          "estimated_traffic": "304"
        },
        {
          "keyword": "employment lawyer near me",
          "position": "15",
          "previous_position": "20",
          "position_change": "+5",
          "url": "https://www.tullylegal.com/new-york-employment-law/",
          "search_volume": "22400",
          "cpc": "2.23",
          "difficulty": "52",
          "estimated_traffic": "281"
        },
        {
          "keyword": "adoption attorney",
          "position": "25",
          "previous_position": "24",
          "position_change": "-1",
          "url": "https://www.tullylegal.com/manhattan-family/adoption/",
          "search_volume": "27100",
          "cpc": "3.44",
          "difficulty": "37",
          "estimated_traffic": "278"
        },
        {
          "keyword": "employment attorney near me",
          "position": "17",
          "previous_position": "20",
          "position_change": "+3",
          "url": "https://www.tullylegal.com/new-york-employment-law/",
          "search_volume": "49500",
          "cpc": "2.23",
          "difficulty": "61",
          "estimated_traffic": "254"
        },
        {
          "keyword": "employment lawyer",
          "position": "20",
          "previous_position": "52",
          "position_change": "+32",
          "url": "https://www.tullylegal.com/new-york-employment-law/",
          "search_volume": "90500",
          "cpc": "2.48",
          "difficulty": "61",
          "estimated_traffic": "253"
        },
        {
          "keyword": "tully rinckey",
          "position": "1",
          "previous_position": "1",
          "position_change": "0",
          "url": "https://www.tullylegal.com/",
          "search_volume": "1500",
          "cpc": "3.97",
          "difficulty": "62",
          "estimated_traffic": "236"
        },
        {
          "keyword": "employee legal",
          "position": "27",
          "previous_position": "14",
          "position_change": "-13",
          "url": "https://www.tullylegal.com/new-york-employment-law/",
          "search_volume": "9900",
          "cpc": "2.75",
          "difficulty": "45",
          "estimated_traffic": "222"
        },
        {
          "keyword": "dissolution of marriage records",
          "position": "6",
          "previous_position": "",
          "position_change": "new",
          "url": "https://www.tullylegal.com/resources/articles/are-new-york-divorce-records-public/",
          "search_volume": "12100",
          "cpc": "0.52",
          "difficulty": "74",
          "estimated_traffic": "209"
        },
        {
          "keyword": "employment law lawyer",
          "position": "16",
          "previous_position": "20",
          "position_change": "+4",
          "url": "https://www.tullylegal.com/new-york-employment-law/",
          "search_volume": "18100",
          "cpc": "2.63",
          "difficulty": "55",
          "estimated_traffic": "159"
        },
        {
          "keyword": "family law attorneys near me",
          "position": "26",
          "previous_position": "",
          "position_change": "new",
          "url": "https://www.tullylegal.com/brooklyn-family/",
          "search_volume": "27100",
          "cpc": "2.75",
          "difficulty": "60",
          "estimated_traffic": "128"
        },
        {
          "keyword": "postnuptial agreement lawyer",
          "position": "22",
          "previous_position": "",
          "position_change": "new",
          "url": "https://www.tullylegal.com/manhattan-family/postnuptial-agreements/",
          "search_volume": "12100",
          "cpc": "4.94",
          "difficulty": "45",
          "estimated_traffic": "128"
        },
        {
          "keyword": "child support attorneys",
          "position": "14",
          "previous_position": "15",
          "position_change": "+1",
          "url": "https://www.tullylegal.com/brooklyn-family/child-support/",
          "search_volume": "10800",
          "cpc": "3.32",
          "difficulty": "46",
          "estimated_traffic": "127"
        },
        {
          "keyword": "employment law lawyers",
          "position": "17",
          "previous_position": "18",
          "position_change": "+1",
          "url": "https://www.tullylegal.com/new-york-employment-law/",
          "search_volume": "22400",
          "cpc": "2.63",
          "difficulty": "55",
          "estimated_traffic": "120"
        },
        {
          "keyword": "employers lawyers",
          "position": "23",
          "previous_position": "23",
          "position_change": "0",
          "url": "https://www.tullylegal.com/new-york-employment-law/",
          "search_volume": "18100",
          "cpc": "2.33",
          "difficulty": "67",
          "estimated_traffic": "105"
        },
        {
          "keyword": "labor law attorney near me",
          "position": "12",
          "previous_position": "",
          "position_change": "new",
          "url": "https://www.tullylegal.com/manhattan-employment-law/",
          "search_volume": "40500",
          "cpc": "2.23",
          "difficulty": "59",
          "estimated_traffic": "102"
        },
        {
          "keyword": "family law lawyers near me",
          "position": "22",
          "previous_position": "",
          "position_change": "new",
          "url": "https://www.tullylegal.com/brooklyn-family/",
          "search_volume": "9900",
          "cpc": "2.75",
          "difficulty": "47",
          "estimated_traffic": "102"
        },
        {
          "keyword": "tully's",
          "position": "2",
          "previous_position": "",
          "position_change": "new",
          "url": "https://www.tullylegal.com/locations/manhattan-ny/?utm_source=google&utm_medium=organic&utm_campaign=gbp&utm_term=NYC&utm_content=homepage",
          "search_volume": "8100",
          "cpc": "0.55",
          "difficulty": "59",
          "estimated_traffic": "93"
        },
        {
          "keyword": "the tully",
          "position": "96",
          "previous_position": "",
          "position_change": "new",
          "url": "https://www.tullylegal.com/locations/manhattan-ny/?utm_source=google&utm_medium=organic&utm_campaign=gbp&utm_term=NYC&utm_content=homepage",
          "search_volume": "590",
          "cpc": "0",
          "difficulty": "16",
          "estimated_traffic": "91"
        },
        {
          "keyword": "premarital agreement",
          "position": "22",
          "previous_position": "",
          "position_change": "new",
          "url": "https://www.tullylegal.com/resources/articles/what-are-the-requirements-for-prenuptial-agreements-in-new-york/",
          "search_volume": "47500",
          "cpc": "5.1",
          "difficulty": "78",
          "estimated_traffic": "81"
        },
        {
          "keyword": "uncontested divorce",
          "position": "23",
          "previous_position": "14",
          "position_change": "-9",
          "url": "https://www.tullylegal.com/resources/articles/what-is-required-for-an-uncontested-divorce-in-new-york-state/",
          "search_volume": "12100",
          "cpc": "2.24",
          "difficulty": "61",
          "estimated_traffic": "76"
        }
      ]
    },
    {
      "filename": "seranking-backlinks-www-dcfesq-com.json",
      "competitorId": "www-dcfesq-com",
      "type": "backlinks",
      "rowCount": 0,
      "topRows": []
    },
    {
      "filename": "seranking-keywords-www-dcfesq-com.json",
      "competitorId": "www-dcfesq-com",
      "type": "positions",
      "rowCount": 100,
      "topRows": [
        {
          "keyword": "dentino",
          "position": "1",
          "previous_position": "1",
          "position_change": "0",
          "url": "https://www.dcfesq.com/",
          "search_volume": "260",
          "cpc": "0",
          "difficulty": "5",
          "estimated_traffic": "33"
        },
        {
          "keyword": "laura fleming",
          "position": "1",
          "previous_position": "1",
          "position_change": "0",
          "url": "https://www.dcfesq.com/lawyers/laura-e-fleming/",
          "search_volume": "260",
          "cpc": "0",
          "difficulty": "6",
          "estimated_traffic": "32"
        },
        {
          "keyword": "dentino cammarata & fazio",
          "position": "1",
          "previous_position": "1",
          "position_change": "0",
          "url": "https://www.dcfesq.com/",
          "search_volume": "70",
          "cpc": "0",
          "difficulty": "7",
          "estimated_traffic": "20"
        },
        {
          "keyword": "jennifer fazio",
          "position": "1",
          "previous_position": "1",
          "position_change": "0",
          "url": "https://www.dcfesq.com/lawyers/fazio/",
          "search_volume": "110",
          "cpc": "0",
          "difficulty": "5",
          "estimated_traffic": "8"
        },
        {
          "keyword": "joseph cammarata",
          "position": "30",
          "previous_position": "36",
          "position_change": "+6",
          "url": "https://www.dcfesq.com/",
          "search_volume": "480",
          "cpc": "0",
          "difficulty": "8",
          "estimated_traffic": "4"
        },
        {
          "keyword": "steven cammarata",
          "position": "1",
          "previous_position": "1",
          "position_change": "0",
          "url": "https://www.dcfesq.com/lawyers/steven-m-cammarata/",
          "search_volume": "30",
          "cpc": "0",
          "difficulty": "6",
          "estimated_traffic": "4"
        },
        {
          "keyword": "ross cammarata",
          "position": "60",
          "previous_position": "60",
          "position_change": "0",
          "url": "http://www.dcfesq.com/",
          "search_volume": "30",
          "cpc": "0",
          "difficulty": "6",
          "estimated_traffic": "4"
        },
        {
          "keyword": "steve cammarata",
          "position": "1",
          "previous_position": "1",
          "position_change": "0",
          "url": "https://www.dcfesq.com/lawyers/steven-m-cammarata/",
          "search_volume": "30",
          "cpc": "0",
          "difficulty": "6",
          "estimated_traffic": "3"
        },
        {
          "keyword": "anthony cammarata",
          "position": "16",
          "previous_position": "",
          "position_change": "new",
          "url": "https://www.dcfesq.com/",
          "search_volume": "110",
          "cpc": "0",
          "difficulty": "6",
          "estimated_traffic": "2"
        },
        {
          "keyword": "jennifer fazio",
          "position": "3",
          "previous_position": "5",
          "position_change": "+2",
          "url": "https://www.dcfesq.com/",
          "search_volume": "110",
          "cpc": "0",
          "difficulty": "5",
          "estimated_traffic": "2"
        },
        {
          "keyword": "ross cammarata",
          "position": "1",
          "previous_position": "1",
          "position_change": "0",
          "url": "https://www.dcfesq.com/lawyers/cammarata/",
          "search_volume": "30",
          "cpc": "0",
          "difficulty": "6",
          "estimated_traffic": "2"
        },
        {
          "keyword": "anthony dentino attorney",
          "position": "2",
          "previous_position": "2",
          "position_change": "0",
          "url": "https://www.dcfesq.com/",
          "search_volume": "10",
          "cpc": "0",
          "difficulty": "7",
          "estimated_traffic": "2"
        },
        {
          "keyword": "dentino cammarata & fazio",
          "position": "1",
          "previous_position": "1",
          "position_change": "0",
          "url": "https://www.dcfesq.com/contact-us/",
          "search_volume": "70",
          "cpc": "0",
          "difficulty": "7",
          "estimated_traffic": "2"
        },
        {
          "keyword": "anthony cammarata",
          "position": "28",
          "previous_position": "",
          "position_change": "new",
          "url": "https://www.dcfesq.com/lawyers/steven-m-cammarata/",
          "search_volume": "110",
          "cpc": "0",
          "difficulty": "6",
          "estimated_traffic": "1"
        },
        {
          "keyword": "laura fazio",
          "position": "16",
          "previous_position": "16",
          "position_change": "0",
          "url": "https://www.dcfesq.com/lawyers/fazio/",
          "search_volume": "90",
          "cpc": "0",
          "difficulty": "7",
          "estimated_traffic": "1"
        },
        {
          "keyword": "mark dycio",
          "position": "22",
          "previous_position": "",
          "position_change": "new",
          "url": "https://www.dcfesq.com/",
          "search_volume": "210",
          "cpc": "0",
          "difficulty": "5",
          "estimated_traffic": "1"
        },
        {
          "keyword": "anthony dentino",
          "position": "3",
          "previous_position": "3",
          "position_change": "0",
          "url": "https://www.dcfesq.com/lawyers/dentino/",
          "search_volume": "30",
          "cpc": "0",
          "difficulty": "9",
          "estimated_traffic": "1"
        },
        {
          "keyword": "cimino law firm",
          "position": "23",
          "previous_position": "29",
          "position_change": "+6",
          "url": "https://www.dcfesq.com/practices/divorce/",
          "search_volume": "170",
          "cpc": "0",
          "difficulty": "10",
          "estimated_traffic": "1"
        },
        {
          "keyword": "jennifer cammarata",
          "position": "30",
          "previous_position": "30",
          "position_change": "0",
          "url": "https://www.dcfesq.com/sitemap/",
          "search_volume": "30",
          "cpc": "0",
          "difficulty": "6",
          "estimated_traffic": "1"
        },
        {
          "keyword": "jennifer cammarata",
          "position": "15",
          "previous_position": "15",
          "position_change": "0",
          "url": "https://www.dcfesq.com/",
          "search_volume": "30",
          "cpc": "0",
          "difficulty": "6",
          "estimated_traffic": "1"
        },
        {
          "keyword": "steve cammarata",
          "position": "6",
          "previous_position": "6",
          "position_change": "0",
          "url": "https://www.dcfesq.com/lawyers/",
          "search_volume": "30",
          "cpc": "0",
          "difficulty": "6",
          "estimated_traffic": "1"
        },
        {
          "keyword": "steve cammarata",
          "position": "2",
          "previous_position": "2",
          "position_change": "0",
          "url": "https://www.dcfesq.com/",
          "search_volume": "30",
          "cpc": "0",
          "difficulty": "6",
          "estimated_traffic": "1"
        },
        {
          "keyword": "steven cammarata",
          "position": "2",
          "previous_position": "2",
          "position_change": "0",
          "url": "https://www.dcfesq.com/lawyers/",
          "search_volume": "30",
          "cpc": "0",
          "difficulty": "6",
          "estimated_traffic": "1"
        },
        {
          "keyword": "anthony dentino attorney rochester ny",
          "position": "2",
          "previous_position": "2",
          "position_change": "0",
          "url": "https://www.dcfesq.com/",
          "search_volume": "10",
          "cpc": "0",
          "difficulty": "7",
          "estimated_traffic": "1"
        },
        {
          "keyword": "anthony dentino attorney rochester ny",
          "position": "1",
          "previous_position": "1",
          "position_change": "0",
          "url": "https://www.dcfesq.com/lawyers/dentino/",
          "search_volume": "10",
          "cpc": "0",
          "difficulty": "7",
          "estimated_traffic": "1"
        }
      ]
    },
    {
      "filename": "seranking-backlinks-www-evansfox-com.json",
      "competitorId": "www-evansfox-com",
      "type": "backlinks",
      "rowCount": 15,
      "topRows": [
        {
          "source_page": "https://hisjourney.org/market/us-ny-rochester-bl-evans-fox-llp-stephen-g-bennett",
          "source_page_title": "Stephen G. Bennett · HisJourney",
          "target_page": "https://www.evansfox.com/attorneys/stephen-bennett/",
          "anchor": "Visit website →",
          "domain_authority": "3",
          "page_authority": "0",
          "nofollow": "no",
          "first_seen": "2026-07-18"
        },
        {
          "source_page": "https://hisjourney.org/market/us-ny-rochester-bl-evans-fox-llp-stephen-g-bennett",
          "source_page_title": "Stephen G. Bennett · HisJourney",
          "target_page": "https://www.evansfox.com/attorneys/stephen-bennett/",
          "anchor": "www.evansfox.com/attorneys/stephen-bennett",
          "domain_authority": "3",
          "page_authority": "0",
          "nofollow": "no",
          "first_seen": "2026-07-18"
        },
        {
          "source_page": "https://www.livewebsites.net/domain-list-421",
          "source_page_title": "livewebsites.net | few of top websites | page no. 421",
          "target_page": "http://evansfox.com/",
          "anchor": "evansfox.com",
          "domain_authority": "7",
          "page_authority": "0",
          "nofollow": "yes",
          "first_seen": "2026-07-15"
        },
        {
          "source_page": "https://www.allreviews.in/domain-list-421",
          "source_page_title": "allreviews.in | few of top websites | page no. 421",
          "target_page": "http://evansfox.com/",
          "anchor": "evansfox.com",
          "domain_authority": "12",
          "page_authority": "0",
          "nofollow": "yes",
          "first_seen": "2026-07-11"
        },
        {
          "source_page": "https://attorneys.regionaldirectory.us/new-york.htm",
          "source_page_title": "New York Attorneys",
          "target_page": "https://evansfox.com/",
          "anchor": "Evans & Fox",
          "domain_authority": "64",
          "page_authority": "13",
          "nofollow": "yes",
          "first_seen": "2026-07-11"
        },
        {
          "source_page": "https://www.ketaki.co.in/domain-list-421",
          "source_page_title": "ketaki.co.in | few of top websites | page no. 421",
          "target_page": "http://evansfox.com/",
          "anchor": "evansfox.com",
          "domain_authority": "12",
          "page_authority": "0",
          "nofollow": "yes",
          "first_seen": "2026-07-11"
        },
        {
          "source_page": "https://www.expertclick.com/19-4419",
          "source_page_title": "Tracy P. Jong -- Tracy Jong Law Firm - Experts",
          "target_page": "http://www.evansfox.com/attorneys/tracy-jong/",
          "anchor": "Jump To Tracy P. Jong -- Tracy Jong Law Firm",
          "domain_authority": "78",
          "page_authority": "0",
          "nofollow": "no",
          "first_seen": "2026-07-11"
        },
        {
          "source_page": "https://www.expertclick.com/12327",
          "source_page_title": "Tracy P. Jong -- Tracy Jong Law Firm - Experts",
          "target_page": "http://www.evansfox.com/attorneys/tracy-jong/",
          "anchor": "Jump To Tracy P. Jong -- Tracy Jong Law Firm",
          "domain_authority": "78",
          "page_authority": "17",
          "nofollow": "no",
          "first_seen": "2026-07-11"
        },
        {
          "source_page": "https://www.expertclick.com/12327",
          "source_page_title": "Tracy P. Jong -- Tracy Jong Law Firm - Experts",
          "target_page": "http://www.evansfox.com/attorneys/tracy-jong/",
          "anchor": "Jump To Tracy P. Jong -- Tracy Jong Law Firm",
          "domain_authority": "78",
          "page_authority": "17",
          "nofollow": "no",
          "first_seen": "2026-07-11"
        },
        {
          "source_page": "https://www.expertclick.com/19-4419",
          "source_page_title": "Tracy P. Jong -- Tracy Jong Law Firm - Experts",
          "target_page": "http://www.evansfox.com/attorneys/tracy-jong/",
          "anchor": "Jump To Tracy P. Jong -- Tracy Jong Law Firm",
          "domain_authority": "78",
          "page_authority": "0",
          "nofollow": "no",
          "first_seen": "2026-07-11"
        },
        {
          "source_page": "https://www.officialwebsites.in/domain-list-421",
          "source_page_title": "officialwebsites.in | few of top websites | page no. 421",
          "target_page": "http://evansfox.com/",
          "anchor": "evansfox.com",
          "domain_authority": "61",
          "page_authority": "0",
          "nofollow": "yes",
          "first_seen": "2026-07-10"
        },
        {
          "source_page": "https://www.showdirectory.in/domain-list-421",
          "source_page_title": "showdirectory.in | few of top websites | page no. 421",
          "target_page": "http://evansfox.com/",
          "anchor": "evansfox.com",
          "domain_authority": "4",
          "page_authority": "0",
          "nofollow": "yes",
          "first_seen": "2026-07-10"
        },
        {
          "source_page": "https://www.cricketlive.co.in/domain-list-421",
          "source_page_title": "cricketlive.co.in | few of top websites | page no. 421",
          "target_page": "http://evansfox.com/",
          "anchor": "evansfox.com",
          "domain_authority": "11",
          "page_authority": "0",
          "nofollow": "yes",
          "first_seen": "2026-07-10"
        },
        {
          "source_page": "https://www.sushila.co.in/domain-list-421",
          "source_page_title": "sushila.co.in | few of top websites | page no. 421",
          "target_page": "http://evansfox.com/",
          "anchor": "evansfox.com",
          "domain_authority": "12",
          "page_authority": "0",
          "nofollow": "yes",
          "first_seen": "2026-07-10"
        },
        {
          "source_page": "https://koronapos.com/blog/how-to-run-a-liquor-store/",
          "source_page_title": "How To Run a Successful Liquor Store",
          "target_page": "https://www.evansfox.com/retail-liquor-license/new-york-state-liquor-authority-enforcement-in-2025/",
          "anchor": "New York’s State Liquor Authority",
          "domain_authority": "74",
          "page_authority": "0",
          "nofollow": "no",
          "first_seen": "2026-06-25"
        }
      ]
    },
    {
      "filename": "seranking-keywords-www-evansfox-com.json",
      "competitorId": "www-evansfox-com",
      "type": "positions",
      "rowCount": 100,
      "topRows": [
        {
          "keyword": "and desist",
          "position": "13",
          "previous_position": "",
          "position_change": "new",
          "url": "https://www.evansfox.com/trademark-cease-and-desist-letter-vlog/",
          "search_volume": "90500",
          "cpc": "0.29",
          "difficulty": "77",
          "estimated_traffic": "280"
        },
        {
          "keyword": "evans fox",
          "position": "1",
          "previous_position": "1",
          "position_change": "0",
          "url": "https://www.evansfox.com/",
          "search_volume": "190",
          "cpc": "0",
          "difficulty": "9",
          "estimated_traffic": "29"
        },
        {
          "keyword": "off license",
          "position": "12",
          "previous_position": "9",
          "position_change": "-3",
          "url": "https://www.evansfox.com/what-on-and-off-premises-liquor-licenses-mean/",
          "search_volume": "5400",
          "cpc": "2.02",
          "difficulty": "70",
          "estimated_traffic": "22"
        },
        {
          "keyword": "cease and desist letter",
          "position": "24",
          "previous_position": "",
          "position_change": "new",
          "url": "https://www.evansfox.com/trademark-cease-and-desist-letter-vlog/",
          "search_volume": "22200",
          "cpc": "0.74",
          "difficulty": "73",
          "estimated_traffic": "16"
        },
        {
          "keyword": "rochester law firm",
          "position": "10",
          "previous_position": "20",
          "position_change": "+10",
          "url": "https://www.evansfox.com/",
          "search_volume": "480",
          "cpc": "2.99",
          "difficulty": "18",
          "estimated_traffic": "15"
        },
        {
          "keyword": "and desist order",
          "position": "14",
          "previous_position": "",
          "position_change": "new",
          "url": "https://www.evansfox.com/trademark-cease-and-desist-letter-vlog/",
          "search_volume": "2400",
          "cpc": "0.5",
          "difficulty": "55",
          "estimated_traffic": "14"
        },
        {
          "keyword": "lawyer rochester",
          "position": "16",
          "previous_position": "18",
          "position_change": "+2",
          "url": "https://www.evansfox.com/",
          "search_volume": "920",
          "cpc": "4.24",
          "difficulty": "22",
          "estimated_traffic": "12"
        },
        {
          "keyword": "attorney rochester",
          "position": "15",
          "previous_position": "17",
          "position_change": "+2",
          "url": "https://www.evansfox.com/",
          "search_volume": "920",
          "cpc": "4.24",
          "difficulty": "24",
          "estimated_traffic": "12"
        },
        {
          "keyword": "evans & evans law firm",
          "position": "14",
          "previous_position": "14",
          "position_change": "0",
          "url": "https://www.evansfox.com/",
          "search_volume": "590",
          "cpc": "4.23",
          "difficulty": "15",
          "estimated_traffic": "12"
        },
        {
          "keyword": "what is an estate",
          "position": "13",
          "previous_position": "",
          "position_change": "new",
          "url": "https://www.evansfox.com/what-is-an-estate/",
          "search_volume": "6600",
          "cpc": "0.05",
          "difficulty": "39",
          "estimated_traffic": "11"
        },
        {
          "keyword": "are confidentiality agreements enforceable",
          "position": "1",
          "previous_position": "",
          "position_change": "new",
          "url": "https://www.evansfox.com/are-employer-confidentiality-and-nondisclosure-agreements-enforceable-in-new-york/",
          "search_volume": "480",
          "cpc": "0.14",
          "difficulty": "21",
          "estimated_traffic": "11"
        },
        {
          "keyword": "bring your own bottle",
          "position": "12",
          "previous_position": "17",
          "position_change": "+5",
          "url": "https://www.evansfox.com/bring-your-own-bottle-byob/",
          "search_volume": "5400",
          "cpc": "0.56",
          "difficulty": "60",
          "estimated_traffic": "10"
        },
        {
          "keyword": "evans legal",
          "position": "15",
          "previous_position": "11",
          "position_change": "-4",
          "url": "https://www.evansfox.com/",
          "search_volume": "480",
          "cpc": "4.07",
          "difficulty": "11",
          "estimated_traffic": "10"
        },
        {
          "keyword": "caterer's permit",
          "position": "3",
          "previous_position": "12",
          "position_change": "+9",
          "url": "https://www.evansfox.com/the-catering-industry-sees-changes-in-new-york-liquor-laws/",
          "search_volume": "320",
          "cpc": "2.11",
          "difficulty": "22",
          "estimated_traffic": "10"
        },
        {
          "keyword": "evans law firm",
          "position": "7",
          "previous_position": "12",
          "position_change": "+5",
          "url": "https://www.evansfox.com/",
          "search_volume": "590",
          "cpc": "4.23",
          "difficulty": "9",
          "estimated_traffic": "9"
        },
        {
          "keyword": "attorneys in rochester",
          "position": "17",
          "previous_position": "15",
          "position_change": "-2",
          "url": "https://www.evansfox.com/",
          "search_volume": "590",
          "cpc": "3.5",
          "difficulty": "21",
          "estimated_traffic": "9"
        },
        {
          "keyword": "rochester ny law firms",
          "position": "21",
          "previous_position": "29",
          "position_change": "+8",
          "url": "https://www.evansfox.com/",
          "search_volume": "480",
          "cpc": "2.99",
          "difficulty": "26",
          "estimated_traffic": "8"
        },
        {
          "keyword": "real estate attorneys rochester ny",
          "position": "8",
          "previous_position": "12",
          "position_change": "+4",
          "url": "https://www.evansfox.com/",
          "search_volume": "480",
          "cpc": "2.33",
          "difficulty": "9",
          "estimated_traffic": "8"
        },
        {
          "keyword": "law firms rochester",
          "position": "16",
          "previous_position": "24",
          "position_change": "+8",
          "url": "https://www.evansfox.com/",
          "search_volume": "590",
          "cpc": "2.93",
          "difficulty": "25",
          "estimated_traffic": "8"
        },
        {
          "keyword": "due diligence period",
          "position": "1",
          "previous_position": "1",
          "position_change": "0",
          "url": "https://www.evansfox.com/understanding-your-due-diligence-period-vlog-november-2024/",
          "search_volume": "480",
          "cpc": "0",
          "difficulty": "32",
          "estimated_traffic": "7"
        },
        {
          "keyword": "law firms in rochester",
          "position": "19",
          "previous_position": "25",
          "position_change": "+6",
          "url": "https://www.evansfox.com/",
          "search_volume": "480",
          "cpc": "2.99",
          "difficulty": "27",
          "estimated_traffic": "7"
        },
        {
          "keyword": "fox and fox",
          "position": "21",
          "previous_position": "19",
          "position_change": "-2",
          "url": "https://www.evansfox.com/",
          "search_volume": "590",
          "cpc": "4.12",
          "difficulty": "8",
          "estimated_traffic": "7"
        },
        {
          "keyword": "arentfox",
          "position": "21",
          "previous_position": "",
          "position_change": "new",
          "url": "https://www.evansfox.com/",
          "search_volume": "3200",
          "cpc": "0",
          "difficulty": "72",
          "estimated_traffic": "7"
        },
        {
          "keyword": "evans attorney at law",
          "position": "17",
          "previous_position": "18",
          "position_change": "+1",
          "url": "https://www.evansfox.com/",
          "search_volume": "210",
          "cpc": "4.62",
          "difficulty": "4",
          "estimated_traffic": "7"
        },
        {
          "keyword": "real estate attorneys in rochester ny",
          "position": "9",
          "previous_position": "14",
          "position_change": "+5",
          "url": "https://www.evansfox.com/",
          "search_volume": "480",
          "cpc": "2.33",
          "difficulty": "6",
          "estimated_traffic": "7"
        }
      ]
    },
    {
      "filename": "seranking-backlinks-www-jmlawfirm-com.json",
      "competitorId": "www-jmlawfirm-com",
      "type": "backlinks",
      "rowCount": 100,
      "topRows": [
        {
          "source_page": "https://www.nycriminaldefense.com/listings/marchioni-associates-llc/",
          "source_page_title": "Marchioni & Associates LLC | NY Criminal Lawyer",
          "target_page": "http://www.jmlawfirm.com/",
          "anchor": "www.jmlawfirm.com",
          "domain_authority": "1",
          "page_authority": "0",
          "nofollow": "no",
          "first_seen": "2026-07-20"
        },
        {
          "source_page": "https://www.grar.org/tips-how-to/oho-agents-getting-started/",
          "source_page_title": "Getting Started with OneHomeowner - for Agents (60 mins) | GRAR | Greater Rochester Association of Realtors",
          "target_page": "https://www.jmlawfirm.com/",
          "anchor": "Marchioni and Associates Law Firm Logo",
          "domain_authority": "50",
          "page_authority": "0",
          "nofollow": "no",
          "first_seen": "2026-07-18"
        },
        {
          "source_page": "https://www.grar.org/tips-how-to/attribution-contact/",
          "source_page_title": "Attribution Contact Info (Agents & Brokers) | GRAR | Greater Rochester Association of Realtors",
          "target_page": "https://www.jmlawfirm.com/",
          "anchor": "Marchioni and Associates Law Firm Logo",
          "domain_authority": "50",
          "page_authority": "0",
          "nofollow": "no",
          "first_seen": "2026-07-18"
        },
        {
          "source_page": "https://www.grar.org/tips-how-to/sign-ordinances/",
          "source_page_title": "Sign Ordinances | GRAR | Greater Rochester Association of Realtors",
          "target_page": "https://www.jmlawfirm.com/",
          "anchor": "Marchioni and Associates Law Firm Logo",
          "domain_authority": "50",
          "page_authority": "0",
          "nofollow": "no",
          "first_seen": "2026-07-18"
        },
        {
          "source_page": "https://www.grar.org/tips-how-to-category/signs/",
          "source_page_title": "Sign Ordinances Archives | GRAR | Greater Rochester Association of Realtors",
          "target_page": "https://www.jmlawfirm.com/",
          "anchor": "Marchioni and Associates Law Firm Logo",
          "domain_authority": "50",
          "page_authority": "0",
          "nofollow": "no",
          "first_seen": "2026-07-17"
        },
        {
          "source_page": "https://www.grar.org/tips-how-to-tag/re-tech/",
          "source_page_title": "RE Tech Archives | GRAR | Greater Rochester Association of Realtors",
          "target_page": "https://www.jmlawfirm.com/",
          "anchor": "Marchioni and Associates Law Firm Logo",
          "domain_authority": "50",
          "page_authority": "0",
          "nofollow": "no",
          "first_seen": "2026-07-17"
        },
        {
          "source_page": "https://www.grar.org/tips-how-to-tag/onehomeowner-settings/",
          "source_page_title": "OneHomeowner settings Archives | GRAR | Greater Rochester Association of Realtors",
          "target_page": "https://www.jmlawfirm.com/",
          "anchor": "Marchioni and Associates Law Firm Logo",
          "domain_authority": "50",
          "page_authority": "0",
          "nofollow": "no",
          "first_seen": "2026-07-17"
        },
        {
          "source_page": "https://www.grar.org/tips-how-to-tag/tech-webinar/",
          "source_page_title": "Tech webinar Archives | GRAR | Greater Rochester Association of Realtors",
          "target_page": "https://www.jmlawfirm.com/",
          "anchor": "Marchioni and Associates Law Firm Logo",
          "domain_authority": "50",
          "page_authority": "0",
          "nofollow": "no",
          "first_seen": "2026-07-17"
        },
        {
          "source_page": "https://www.grar.org/category/market/",
          "source_page_title": "Market Updates Archives | GRAR | Greater Rochester Association of Realtors",
          "target_page": "https://www.jmlawfirm.com/",
          "anchor": "Marchioni and Associates Law Firm Logo",
          "domain_authority": "50",
          "page_authority": "0",
          "nofollow": "no",
          "first_seen": "2026-07-17"
        },
        {
          "source_page": "https://www.grar.org/findings-of-fact/",
          "source_page_title": "Ethics Panel/Citation Case \"Findings of Fact\" | GRAR | Greater Rochester Association of Realtors",
          "target_page": "https://www.jmlawfirm.com/",
          "anchor": "Marchioni and Associates Law Firm Logo",
          "domain_authority": "50",
          "page_authority": "0",
          "nofollow": "no",
          "first_seen": "2026-07-17"
        },
        {
          "source_page": "https://www.grar.org/rbj-presents-the-2026-power-list-for-construction-real-estate/",
          "source_page_title": "RBJ presents the 2026 Power List for Construction & Real Estate | GRAR | Greater Rochester Association of Realtors",
          "target_page": "https://www.jmlawfirm.com/",
          "anchor": "Marchioni and Associates Law Firm Logo",
          "domain_authority": "50",
          "page_authority": "0",
          "nofollow": "no",
          "first_seen": "2026-07-17"
        },
        {
          "source_page": "https://www.grar.org/tips-how-to-tag/tech-tips/",
          "source_page_title": "Tech tips Archives | GRAR | Greater Rochester Association of Realtors",
          "target_page": "https://www.jmlawfirm.com/",
          "anchor": "Marchioni and Associates Law Firm Logo",
          "domain_authority": "50",
          "page_authority": "0",
          "nofollow": "no",
          "first_seen": "2026-07-17"
        },
        {
          "source_page": "https://www.grar.org/ardi-sabor-lera/",
          "source_page_title": "Case Study: Ardi Transformed Member Support for SABOR and LERA MLS | GRAR | Greater Rochester Association of Realtors",
          "target_page": "https://www.jmlawfirm.com/",
          "anchor": "Marchioni and Associates Law Firm Logo",
          "domain_authority": "50",
          "page_authority": "0",
          "nofollow": "no",
          "first_seen": "2026-07-17"
        },
        {
          "source_page": "https://www.grar.org/compliance/",
          "source_page_title": "Compliance & Rules | GRAR | Greater Rochester Association of Realtors",
          "target_page": "https://www.jmlawfirm.com/",
          "anchor": "Marchioni and Associates Law Firm Logo",
          "domain_authority": "50",
          "page_authority": "0",
          "nofollow": "no",
          "first_seen": "2026-07-17"
        },
        {
          "source_page": "https://www.grar.org/tips-how-to-tag/onehomeowner-contacts/",
          "source_page_title": "OneHomeowner contacts Archives | GRAR | Greater Rochester Association of Realtors",
          "target_page": "https://www.jmlawfirm.com/",
          "anchor": "Marchioni and Associates Law Firm Logo",
          "domain_authority": "50",
          "page_authority": "0",
          "nofollow": "no",
          "first_seen": "2026-07-17"
        },
        {
          "source_page": "https://www.grar.org/tips-how-to-tag/real-estate-signs/",
          "source_page_title": "Real estate signs Archives | GRAR | Greater Rochester Association of Realtors",
          "target_page": "https://www.jmlawfirm.com/",
          "anchor": "Marchioni and Associates Law Firm Logo",
          "domain_authority": "50",
          "page_authority": "0",
          "nofollow": "no",
          "first_seen": "2026-07-17"
        },
        {
          "source_page": "https://www.grar.org/demo-member-support/",
          "source_page_title": "[ DEMO ] Member Support | GRAR | Greater Rochester Association of Realtors",
          "target_page": "https://www.jmlawfirm.com/",
          "anchor": "Marchioni and Associates Law Firm Logo",
          "domain_authority": "50",
          "page_authority": "0",
          "nofollow": "no",
          "first_seen": "2026-07-17"
        },
        {
          "source_page": "https://www.grar.org/experienced-realtors-anchor-the-industry/",
          "source_page_title": "Experienced REALTORS® Anchor the Industry as Housing Affordability Remains Top Hurdle, New NAR Report Finds | GRAR | Greater Rochester Association of Realtors",
          "target_page": "https://www.jmlawfirm.com/",
          "anchor": "Marchioni and Associates Law Firm Logo",
          "domain_authority": "50",
          "page_authority": "0",
          "nofollow": "no",
          "first_seen": "2026-07-17"
        },
        {
          "source_page": "https://www.grar.org/tips-how-to-tag/articles/",
          "source_page_title": "Articles Archives | GRAR | Greater Rochester Association of Realtors",
          "target_page": "https://www.jmlawfirm.com/",
          "anchor": "Marchioni and Associates Law Firm Logo",
          "domain_authority": "50",
          "page_authority": "0",
          "nofollow": "no",
          "first_seen": "2026-07-17"
        },
        {
          "source_page": "https://www.grar.org/tips-how-to-tag/sign-ordinance/",
          "source_page_title": "Sign ordinance Archives | GRAR | Greater Rochester Association of Realtors",
          "target_page": "https://www.jmlawfirm.com/",
          "anchor": "Marchioni and Associates Law Firm Logo",
          "domain_authority": "50",
          "page_authority": "0",
          "nofollow": "no",
          "first_seen": "2026-07-17"
        },
        {
          "source_page": "https://www.grar.org/tips-how-to-tag/teams-settings/",
          "source_page_title": "Teams settings Archives | GRAR | Greater Rochester Association of Realtors",
          "target_page": "https://www.jmlawfirm.com/",
          "anchor": "Marchioni and Associates Law Firm Logo",
          "domain_authority": "50",
          "page_authority": "0",
          "nofollow": "no",
          "first_seen": "2026-07-17"
        },
        {
          "source_page": "https://www.grar.org/tips-how-to/getting-started-retech/",
          "source_page_title": "Getting Started with RE Technology Webinar (25 mins) | GRAR | Greater Rochester Association of Realtors",
          "target_page": "https://www.jmlawfirm.com/",
          "anchor": "Marchioni and Associates Law Firm Logo",
          "domain_authority": "50",
          "page_authority": "0",
          "nofollow": "no",
          "first_seen": "2026-07-17"
        },
        {
          "source_page": "https://www.grar.org/news-events/",
          "source_page_title": "News & Events | GRAR | Greater Rochester Association of Realtors",
          "target_page": "https://www.jmlawfirm.com/",
          "anchor": "Marchioni and Associates Law Firm Logo",
          "domain_authority": "50",
          "page_authority": "0",
          "nofollow": "no",
          "first_seen": "2026-07-16"
        },
        {
          "source_page": "https://www.grar.org/ardi-mibor/",
          "source_page_title": "Case Study: Ardi Handles 3,200 Questions and Tech Support for MIBOR | GRAR | Greater Rochester Association of Realtors",
          "target_page": "https://www.jmlawfirm.com/",
          "anchor": "Marchioni and Associates Law Firm Logo",
          "domain_authority": "50",
          "page_authority": "0",
          "nofollow": "no",
          "first_seen": "2026-07-16"
        },
        {
          "source_page": "https://www.grar.org/category/ps/",
          "source_page_title": "Products & Services Archives | GRAR | Greater Rochester Association of Realtors",
          "target_page": "https://www.jmlawfirm.com/",
          "anchor": "Marchioni and Associates Law Firm Logo",
          "domain_authority": "50",
          "page_authority": "0",
          "nofollow": "no",
          "first_seen": "2026-07-16"
        }
      ]
    },
    {
      "filename": "seranking-keywords-www-jmlawfirm-com.json",
      "competitorId": "www-jmlawfirm-com",
      "type": "positions",
      "rowCount": 100,
      "topRows": [
        {
          "keyword": "marchioni and associates",
          "position": "1",
          "previous_position": "",
          "position_change": "new",
          "url": "https://www.jmlawfirm.com/",
          "search_volume": "590",
          "cpc": "0",
          "difficulty": "8",
          "estimated_traffic": "108"
        },
        {
          "keyword": "john marchioni",
          "position": "1",
          "previous_position": "",
          "position_change": "new",
          "url": "https://www.jmlawfirm.com/",
          "search_volume": "210",
          "cpc": "3.05",
          "difficulty": "7",
          "estimated_traffic": "30"
        },
        {
          "keyword": "real estate attorneys rochester ny",
          "position": "4",
          "previous_position": "5",
          "position_change": "+1",
          "url": "https://www.jmlawfirm.com/",
          "search_volume": "480",
          "cpc": "2.33",
          "difficulty": "9",
          "estimated_traffic": "14"
        },
        {
          "keyword": "rochester law firm",
          "position": "24",
          "previous_position": "55",
          "position_change": "+31",
          "url": "https://www.jmlawfirm.com/our-team/attorneys",
          "search_volume": "480",
          "cpc": "2.99",
          "difficulty": "18",
          "estimated_traffic": "14"
        },
        {
          "keyword": "real estate attorneys in rochester ny",
          "position": "4",
          "previous_position": "4",
          "position_change": "0",
          "url": "https://www.jmlawfirm.com/",
          "search_volume": "480",
          "cpc": "2.33",
          "difficulty": "6",
          "estimated_traffic": "14"
        },
        {
          "keyword": "rochester ny legal jobs",
          "position": "25",
          "previous_position": "25",
          "position_change": "0",
          "url": "https://www.jmlawfirm.com/careers",
          "search_volume": "390",
          "cpc": "0.1",
          "difficulty": "5",
          "estimated_traffic": "13"
        },
        {
          "keyword": "marchioni and associates",
          "position": "1",
          "previous_position": "",
          "position_change": "new",
          "url": "https://www.jmlawfirm.com/our-team/attorneys",
          "search_volume": "590",
          "cpc": "0",
          "difficulty": "8",
          "estimated_traffic": "12"
        },
        {
          "keyword": "marchioni and associates",
          "position": "79",
          "previous_position": "47",
          "position_change": "-32",
          "url": "http://www.jmlawfirm.com/",
          "search_volume": "590",
          "cpc": "0",
          "difficulty": "8",
          "estimated_traffic": "12"
        },
        {
          "keyword": "attorney positions rochester ny",
          "position": "29",
          "previous_position": "29",
          "position_change": "0",
          "url": "https://www.jmlawfirm.com/careers",
          "search_volume": "320",
          "cpc": "0.02",
          "difficulty": "8",
          "estimated_traffic": "12"
        },
        {
          "keyword": "legal jobs rochester new york",
          "position": "29",
          "previous_position": "30",
          "position_change": "+1",
          "url": "https://www.jmlawfirm.com/careers",
          "search_volume": "390",
          "cpc": "0.1",
          "difficulty": "6",
          "estimated_traffic": "10"
        },
        {
          "keyword": "real estate attorneys rochester ny",
          "position": "1",
          "previous_position": "2",
          "position_change": "+1",
          "url": "http://www.jmlawfirm.com/",
          "search_volume": "480",
          "cpc": "2.33",
          "difficulty": "9",
          "estimated_traffic": "9"
        },
        {
          "keyword": "attorney rochester",
          "position": "25",
          "previous_position": "55",
          "position_change": "+30",
          "url": "https://www.jmlawfirm.com/our-team/attorneys",
          "search_volume": "920",
          "cpc": "4.24",
          "difficulty": "24",
          "estimated_traffic": "9"
        },
        {
          "keyword": "real estate attorney rochester ny",
          "position": "1",
          "previous_position": "",
          "position_change": "new",
          "url": "http://www.jmlawfirm.com/",
          "search_volume": "480",
          "cpc": "2.33",
          "difficulty": "8",
          "estimated_traffic": "8"
        },
        {
          "keyword": "real estate lawyer rochester ny",
          "position": "1",
          "previous_position": "",
          "position_change": "new",
          "url": "http://www.jmlawfirm.com/",
          "search_volume": "480",
          "cpc": "2.33",
          "difficulty": "8",
          "estimated_traffic": "8"
        },
        {
          "keyword": "lawyer rochester",
          "position": "27",
          "previous_position": "29",
          "position_change": "+2",
          "url": "https://www.jmlawfirm.com/our-team/attorneys",
          "search_volume": "920",
          "cpc": "4.24",
          "difficulty": "22",
          "estimated_traffic": "8"
        },
        {
          "keyword": "real estate attorneys in rochester ny",
          "position": "1",
          "previous_position": "",
          "position_change": "new",
          "url": "http://www.jmlawfirm.com/",
          "search_volume": "480",
          "cpc": "2.33",
          "difficulty": "6",
          "estimated_traffic": "8"
        },
        {
          "keyword": "rochester ny real estate attorney",
          "position": "1",
          "previous_position": "1",
          "position_change": "0",
          "url": "http://www.jmlawfirm.com/",
          "search_volume": "480",
          "cpc": "2.33",
          "difficulty": "6",
          "estimated_traffic": "8"
        },
        {
          "keyword": "legal jobs rochester ny",
          "position": "30",
          "previous_position": "31",
          "position_change": "+1",
          "url": "https://www.jmlawfirm.com/careers",
          "search_volume": "390",
          "cpc": "0.1",
          "difficulty": "5",
          "estimated_traffic": "7"
        },
        {
          "keyword": "real estate attorney rochester ny",
          "position": "5",
          "previous_position": "5",
          "position_change": "0",
          "url": "https://www.jmlawfirm.com/",
          "search_volume": "480",
          "cpc": "2.33",
          "difficulty": "8",
          "estimated_traffic": "7"
        },
        {
          "keyword": "real estate lawyer rochester ny",
          "position": "6",
          "previous_position": "4",
          "position_change": "-2",
          "url": "https://www.jmlawfirm.com/",
          "search_volume": "480",
          "cpc": "2.33",
          "difficulty": "8",
          "estimated_traffic": "7"
        },
        {
          "keyword": "john marchioni attorney",
          "position": "1",
          "previous_position": "1",
          "position_change": "0",
          "url": "https://www.jmlawfirm.com/",
          "search_volume": "40",
          "cpc": "0",
          "difficulty": "10",
          "estimated_traffic": "7"
        },
        {
          "keyword": "john marchioni",
          "position": "3",
          "previous_position": "",
          "position_change": "new",
          "url": "https://www.jmlawfirm.com/our-team/attorneys",
          "search_volume": "210",
          "cpc": "3.05",
          "difficulty": "7",
          "estimated_traffic": "7"
        },
        {
          "keyword": "marchioni and associates",
          "position": "1",
          "previous_position": "",
          "position_change": "new",
          "url": "https://www.jmlawfirm.com/contact",
          "search_volume": "590",
          "cpc": "0",
          "difficulty": "8",
          "estimated_traffic": "6"
        },
        {
          "keyword": "rochester ny real estate attorney",
          "position": "5",
          "previous_position": "5",
          "position_change": "0",
          "url": "https://www.jmlawfirm.com/",
          "search_volume": "480",
          "cpc": "2.33",
          "difficulty": "6",
          "estimated_traffic": "6"
        },
        {
          "keyword": "attorneys in rochester",
          "position": "29",
          "previous_position": "22",
          "position_change": "-7",
          "url": "https://www.jmlawfirm.com/our-team/attorneys",
          "search_volume": "590",
          "cpc": "3.5",
          "difficulty": "21",
          "estimated_traffic": "5"
        }
      ]
    },
    {
      "filename": "seranking-backlinks-www-trevettcristo-com.json",
      "competitorId": "www-trevettcristo-com",
      "type": "backlinks",
      "rowCount": 0,
      "topRows": []
    },
    {
      "filename": "seranking-keywords-www-trevettcristo-com.json",
      "competitorId": "www-trevettcristo-com",
      "type": "positions",
      "rowCount": 100,
      "topRows": [
        {
          "keyword": "trevett cristo attorneys",
          "position": "1",
          "previous_position": "1",
          "position_change": "0",
          "url": "https://www.trevettcristo.com/",
          "search_volume": "480",
          "cpc": "3.15",
          "difficulty": "10",
          "estimated_traffic": "113"
        },
        {
          "keyword": "trevett cristo",
          "position": "1",
          "previous_position": "1",
          "position_change": "0",
          "url": "https://www.trevettcristo.com/",
          "search_volume": "480",
          "cpc": "3.15",
          "difficulty": "9",
          "estimated_traffic": "106"
        },
        {
          "keyword": "lawyer rochester",
          "position": "4",
          "previous_position": "5",
          "position_change": "+1",
          "url": "https://www.trevettcristo.com/",
          "search_volume": "920",
          "cpc": "4.24",
          "difficulty": "22",
          "estimated_traffic": "32"
        },
        {
          "keyword": "attorney rochester",
          "position": "5",
          "previous_position": "10",
          "position_change": "+5",
          "url": "https://www.trevettcristo.com/",
          "search_volume": "920",
          "cpc": "4.24",
          "difficulty": "24",
          "estimated_traffic": "18"
        },
        {
          "keyword": "real estate attorneys rochester ny",
          "position": "3",
          "previous_position": "13",
          "position_change": "+10",
          "url": "https://www.trevettcristo.com/speciality/residential-real-estate",
          "search_volume": "480",
          "cpc": "2.33",
          "difficulty": "9",
          "estimated_traffic": "17"
        },
        {
          "keyword": "rochester law firm",
          "position": "16",
          "previous_position": "9",
          "position_change": "-7",
          "url": "https://www.trevettcristo.com/",
          "search_volume": "480",
          "cpc": "2.99",
          "difficulty": "18",
          "estimated_traffic": "17"
        },
        {
          "keyword": "trevett cristo attorneys",
          "position": "1",
          "previous_position": "1",
          "position_change": "0",
          "url": "https://www.trevettcristo.com/attorneys",
          "search_volume": "480",
          "cpc": "3.15",
          "difficulty": "10",
          "estimated_traffic": "16"
        },
        {
          "keyword": "trevett cristo attorneys",
          "position": "27",
          "previous_position": "28",
          "position_change": "+1",
          "url": "http://www.trevettcristo.com/",
          "search_volume": "480",
          "cpc": "3.15",
          "difficulty": "10",
          "estimated_traffic": "14"
        },
        {
          "keyword": "real estate attorney rochester ny",
          "position": "4",
          "previous_position": "6",
          "position_change": "+2",
          "url": "https://www.trevettcristo.com/speciality/residential-real-estate",
          "search_volume": "480",
          "cpc": "2.33",
          "difficulty": "8",
          "estimated_traffic": "12"
        },
        {
          "keyword": "attorney rochester",
          "position": "30",
          "previous_position": "25",
          "position_change": "-5",
          "url": "https://www.trevettcristo.com/attorneys",
          "search_volume": "920",
          "cpc": "4.24",
          "difficulty": "24",
          "estimated_traffic": "11"
        },
        {
          "keyword": "trevett cristo",
          "position": "1",
          "previous_position": "1",
          "position_change": "0",
          "url": "https://www.trevettcristo.com/attorneys",
          "search_volume": "480",
          "cpc": "3.15",
          "difficulty": "9",
          "estimated_traffic": "11"
        },
        {
          "keyword": "trevett cristo",
          "position": "48",
          "previous_position": "35",
          "position_change": "-13",
          "url": "http://www.trevettcristo.com/",
          "search_volume": "480",
          "cpc": "3.15",
          "difficulty": "9",
          "estimated_traffic": "10"
        },
        {
          "keyword": "david coletti",
          "position": "1",
          "previous_position": "1",
          "position_change": "0",
          "url": "https://www.trevettcristo.com/article/david-coletti-joins-trevett-cristo-pc-partner",
          "search_volume": "70",
          "cpc": "0",
          "difficulty": "5",
          "estimated_traffic": "9"
        },
        {
          "keyword": "david ealy",
          "position": "1",
          "previous_position": "1",
          "position_change": "0",
          "url": "https://www.trevettcristo.com/attorneys/david-h-ealy",
          "search_volume": "70",
          "cpc": "0",
          "difficulty": "6",
          "estimated_traffic": "9"
        },
        {
          "keyword": "rochester employment attorneys",
          "position": "22",
          "previous_position": "21",
          "position_change": "-1",
          "url": "https://www.trevettcristo.com/speciality/individual-employment",
          "search_volume": "590",
          "cpc": "1.67",
          "difficulty": "13",
          "estimated_traffic": "9"
        },
        {
          "keyword": "attorneys in rochester",
          "position": "15",
          "previous_position": "24",
          "position_change": "+9",
          "url": "https://www.trevettcristo.com/attorneys",
          "search_volume": "590",
          "cpc": "3.5",
          "difficulty": "21",
          "estimated_traffic": "8"
        },
        {
          "keyword": "rochester ny law firms",
          "position": "23",
          "previous_position": "12",
          "position_change": "-11",
          "url": "https://www.trevettcristo.com/",
          "search_volume": "480",
          "cpc": "2.99",
          "difficulty": "26",
          "estimated_traffic": "7"
        },
        {
          "keyword": "attorney david ross",
          "position": "6",
          "previous_position": "9",
          "position_change": "+3",
          "url": "https://www.trevettcristo.com/attorneys/david-g-ross",
          "search_volume": "140",
          "cpc": "0",
          "difficulty": "5",
          "estimated_traffic": "7"
        },
        {
          "keyword": "ny child support payments",
          "position": "21",
          "previous_position": "",
          "position_change": "new",
          "url": "https://www.trevettcristo.com/article/basics-getting-child-support-new-york-state",
          "search_volume": "320",
          "cpc": "0",
          "difficulty": "29",
          "estimated_traffic": "7"
        },
        {
          "keyword": "agreement in business",
          "position": "29",
          "previous_position": "",
          "position_change": "new",
          "url": "https://www.trevettcristo.com/article/3-must-have-contract-agreements-startup-businesses",
          "search_volume": "590",
          "cpc": "1.94",
          "difficulty": "18",
          "estimated_traffic": "7"
        },
        {
          "keyword": "attorneys rochester new york",
          "position": "12",
          "previous_position": "",
          "position_change": "new",
          "url": "https://www.trevettcristo.com/",
          "search_volume": "370",
          "cpc": "4.24",
          "difficulty": "16",
          "estimated_traffic": "6"
        },
        {
          "keyword": "law firms rochester ny",
          "position": "13",
          "previous_position": "13",
          "position_change": "0",
          "url": "https://www.trevettcristo.com/",
          "search_volume": "480",
          "cpc": "2.99",
          "difficulty": "28",
          "estimated_traffic": "6"
        },
        {
          "keyword": "melanie slaughter",
          "position": "4",
          "previous_position": "4",
          "position_change": "0",
          "url": "https://www.trevettcristo.com/attorneys/melanie-slaughter-wolk",
          "search_volume": "320",
          "cpc": "0",
          "difficulty": "4",
          "estimated_traffic": "6"
        },
        {
          "keyword": "attorney rochester new york",
          "position": "17",
          "previous_position": "11",
          "position_change": "-6",
          "url": "https://www.trevettcristo.com/",
          "search_volume": "370",
          "cpc": "4.24",
          "difficulty": "18",
          "estimated_traffic": "6"
        },
        {
          "keyword": "law firms in rochester",
          "position": "23",
          "previous_position": "54",
          "position_change": "+31",
          "url": "https://www.trevettcristo.com/our-firm",
          "search_volume": "480",
          "cpc": "2.99",
          "difficulty": "27",
          "estimated_traffic": "6"
        }
      ]
    }
  ]
}